mkdocs_nav_weight/__init__.py
mkdocs_nav_weight/nav_setter.py
mkdocs_nav_weight/util.py
mkdocs_nav_weight-0.2.0.dist-info/LICENSE
mkdocs_nav_weight-0.2.0.dist-info/METADATA
mkdocs_nav_weight-0.2.0.dist-info/WHEEL
mkdocs_nav_weight-0.2.0.dist-info/entry_points.txt
mkdocs_nav_weight-0.2.0.dist-info/top_level.txt
mkdocs_nav_weight-0.2.0.dist-info/RECORD
