Metadata-Version: 2.1
Name: mkdocs-nav-weight
Version: 0.2.0
Summary: A simple mkdocs plugin, enables to organize Navigation in a more markdownic way.
Home-page: https://github.com/shu307/mkdocs-nav-weight
Author: shu307
Author-email: shu307@qq.com
License: MIT
License-File: LICENSE
Requires-Dist: mkdocs >=1
